python_docker_app/__init__.py
python_docker_app/cli.py
python_docker_app/assets/example.txt
python_docker_app-0.0.1.dist-info/licenses/LICENSE
python_docker_app-0.0.1.dist-info/METADATA
python_docker_app-0.0.1.dist-info/WHEEL
python_docker_app-0.0.1.dist-info/entry_points.txt
python_docker_app-0.0.1.dist-info/top_level.txt
python_docker_app-0.0.1.dist-info/RECORD
