Metadata-Version: 2.4
Name: python-docker-app
Version: 0.0.1
Summary: python docker appification
Home-page: https://github.com/zackees/python-docker-app
Maintainer: Zachary Vorhies
License: BSD 3-Clause License
Keywords: template-python-cmd
Classifier: Programming Language :: Python :: 3
Requires-Python: >=3.10
License-File: LICENSE
Dynamic: home-page
Dynamic: license-file
Dynamic: maintainer
